cliborg/__init__.py
cliborg/cliborg.py
cliborg-0.1.2.dist-info/LICENSE
cliborg-0.1.2.dist-info/METADATA
cliborg-0.1.2.dist-info/WHEEL
cliborg-0.1.2.dist-info/entry_points.txt
cliborg-0.1.2.dist-info/top_level.txt
cliborg-0.1.2.dist-info/RECORD
