Metadata-Version: 2.1
Name: cliborg
Version: 0.1.2
Summary: A command-line tool for querying Ollama models
Home-page: https://github.com/yourusername/cliborg
Author: Mohamed Taher
Author-email: algorhym3@gmail.com
Classifier: Programming Language :: Python :: 3
Classifier: License :: OSI Approved :: MIT License
Classifier: Operating System :: OS Independent
Requires-Python: >=3.6
License-File: LICENSE
Requires-Dist: requests
Requires-Dist: click
Requires-Dist: ollama
